{
  "title": "TG-TET-JUNE-2025 NOTIFICATION FOR ONLINE APPLICATIONS",
  "outline": [
    {
      "level": "H3",
      "text": "TG-TET Cell O/o the Director, SCERT",
      "page": 1
    },
    {
      "level": "H3",
      "text": "Opp. E.Gate, LB Stadium, Basheerbagh, Hyderabad-500001.",
      "page": 1
    },
    {
      "level": "H3",
      "text": "TG-TET Office - Mobile Phone Nos.:",
      "page": 1
    },
    {
      "level": "H1",
      "text": "7093708883 / 7093708884",
      "page": 1
    },
    {
      "level": "H1",
      "text": "7093958881 / 7093468882",
      "page": 1
    },
    {
      "level": "H1",
      "text": "Rc.No.",
      "page": 1
    },
    {
      "level": "H1",
      "text": "225/TGTET-JUNE-2025",
      "page": 1
    },
    {
      "level": "H1",
      "text": "Dt.11.04.2025",
      "page": 1
    },
    {
      "level": "H1",
      "text": "Re:",
      "page": 1
    },
    {
      "level": "H3",
      "text": ".O.Ms.No.36 School Education (Trg,) Dept., dt 23.12.2015",
      "page": 1
    },
    {
      "level": "H3",
      "text": "G.O.Ms. No.8 School Education (Ser.III) Dept., dt 23.03.2022",
      "page": 1
    },
    {
      "level": "H3",
      "text": "G.O.Ms.No.18 School Education (Ser.III) Dept., dt 05.07.2024",
      "page": 1
    },
    {
      "level": "H3",
      "text": "G.O.Ms.No.90, Finance (HRM.VII) Dept. Dt.07.08.2024-I I(Issue of",
      "page": 1
    },
    {
      "level": "H3",
      "text": "Job Calendar for 2024-25)",
      "page": 1
    },
    {
      "level": "H3",
      "text": "Memo No.2198/Ser.III/2024 dt.07.04.2025",
      "page": 1
    },
    {
      "level": "H3",
      "text": "Online applications are invited from eligible candidates who intend to be teachers for",
      "page": 1
    },
    {
      "level": "H3",
      "text": "Classes I to VIII in schools in Telangana State for appearing for the Telangana",
      "page": 1
    },
    {
      "level": "H3",
      "text": "Teacher Eligibility Test (TG-TET-JUNE-2025) to be conducted ONLINE as",
      "page": 1
    },
    {
      "level": "H3",
      "text": "Computer Based Test (CBT) by Department of School Education, Government of",
      "page": 1
    },
    {
      "level": "H3",
      "text": "Telangana State between 15.06.2025 and 30.06.2025.",
      "page": 1
    },
    {
      "level": "H3",
      "text": "In accordance with the provisions of Sub — Section (1) of Section 23 of the Right to",
      "page": 1
    },
    {
      "level": "H3",
      "text": "Education Act (RTE), 2009, the National Council for Teacher Education (NCTE) had",
      "page": 1
    },
    {
      "level": "H3",
      "text": "vide its Notification dated 23rd August, 2010 laid down the minimum qualifications",
      "page": 1
    },
    {
      "level": "H3",
      "text": "for a person to be eligible for appointment as a teacher for classes I to VIII. It had been",
      "page": 1
    },
    {
      "level": "H3",
      "text": "inter alia provided that one of the essential qualifications for a person to be eligible for",
      "page": 1
    },
    {
      "level": "H3",
      "text": "appointment as a teacher in any of the schools referred to in clause (n) of section 2 of",
      "page": 1
    },
    {
      "level": "H3",
      "text": "the RTE Act is that she / he should pass the Teacher Eligibility Test (TET) which will",
      "page": 1
    },
    {
      "level": "H3",
      "text": "be conducted by the appropriate Government in accordance with the Guidelines",
      "page": 1
    },
    {
      "level": "H3",
      "text": "framed by the NCTE. Accordingly, Government of Telangana State has issued",
      "page": 1
    },
    {
      "level": "H3",
      "text": "guidelines for conducting Teacher Eligibility Test in Telangana State vide G.O’s 1st,",
      "page": 1
    },
    {
      "level": "H3",
      "text": "2nd and 3rd cited in the reference above.",
      "page": 1
    },
    {
      "level": "H3",
      "text": "All candidates who possess D.El Ed./ D.Ed. / B.Ed. / Language Pandit or equivalent",
      "page": 1
    },
    {
      "level": "H3",
      "text": "qualifications and candidates pursuing final year of the said courses with requisite",
      "page": 1
    },
    {
      "level": "H3",
      "text": "percentage of marks obtained as given in the Information Bulletin of TG-TET-JUNE-",
      "page": 1
    },
    {
      "level": "H3",
      "text": "2025 and who aspire to become teachers for Classes I to VIII in the schools of the",
      "page": 1
    },
    {
      "level": "H3",
      "text": "State Government, Mandal Parishad, Zilla Parishad Schools, Private Aided Schools",
      "page": 1
    },
    {
      "level": "H3",
      "text": "and Private unaided schools in Telangana State can appear for TG-TET-JUNE-2025.",
      "page": 1
    },
    {
      "level": "H3",
      "text": "Further, the candidates who got qualified in the earlier TETs can also apply for TG-",
      "page": 1
    },
    {
      "level": "H3",
      "text": "TET-JUNE-2025, if they desire improvement over their previous TET score.",
      "page": 1
    },
    {
      "level": "H3",
      "text": "TG-TET-JUNE-2025 will be conducted in 2 papers viz. Paper-I & Paper-II. The",
      "page": 2
    },
    {
      "level": "H3",
      "text": "candidates who intend to be teachers for classes I to V have to appear for Paper-I and",
      "page": 2
    },
    {
      "level": "H3",
      "text": "the candidates who intend to be teachers for classes VI to VIII have to appear for",
      "page": 2
    },
    {
      "level": "H3",
      "text": "Paper-II. The candidates who intend to be teachers for all classes from I to VIII have to",
      "page": 2
    },
    {
      "level": "H3",
      "text": "appear for both papers i.e. Paper-I and Paper-II.",
      "page": 2
    },
    {
      "level": "H3",
      "text": "Date and Timings",
      "page": 2
    },
    {
      "level": "H3",
      "text": "TG-TET-JUNE-2025 will be conducted ONLINE as Computer Based Test as given",
      "page": 2
    },
    {
      "level": "H3",
      "text": "below:",
      "page": 2
    },
    {
      "level": "H3",
      "text": "Dates of Exam",
      "page": 2
    },
    {
      "level": "H3",
      "text": "Morning Session Timings",
      "page": 2
    },
    {
      "level": "H3",
      "text": "Afternoon Session Timings",
      "page": 2
    },
    {
      "level": "H3",
      "text": "Between 15.06.2025",
      "page": 2
    },
    {
      "level": "H3",
      "text": "and 30.06.2025",
      "page": 2
    },
    {
      "level": "H3",
      "text": "(2 Hours 30 Minutes)",
      "page": 2
    },
    {
      "level": "H3",
      "text": "2.00 PM to 4.30 PM",
      "page": 2
    },
    {
      "level": "H3",
      "text": "(2 Hours 30 Minutes)",
      "page": 2
    },
    {
      "level": "H3",
      "text": "Exam fee:",
      "page": 2
    },
    {
      "level": "H3",
      "text": "The exam fee prescribed for appearing for TGTET-JUNE-2025 is Rs. 750.00 (Rupees",
      "page": 2
    },
    {
      "level": "H3",
      "text": "Seven Hundred and Fifty only) for either only Paper I or only Paper II and Rs.1000",
      "page": 2
    },
    {
      "level": "H3",
      "text": "(Rupees One Thousand Only) for those appearing for both Papers I and II. Candidates",
      "page": 2
    },
    {
      "level": "H3",
      "text": "can pay the exam fee through Online payment option provided at the website",
      "page": 2
    },
    {
      "level": "H3",
      "text": "https://schooledu.telangana.gov.in",
      "page": 2
    },
    {
      "level": "H3",
      "text": "from 15.04.2025 to 30.04.2025.",
      "page": 2
    },
    {
      "level": "H3",
      "text": "Submission of application:",
      "page": 2
    },
    {
      "level": "H3",
      "text": "Detailed procedure for applying ONLINE is given in the Information Bulletin.",
      "page": 2
    },
    {
      "level": "H3",
      "text": "Candidates can download the 'Information Bulletin' free of cost from the website",
      "page": 2
    },
    {
      "level": "H3",
      "text": "https://schooledu.telangana.gov.in",
      "page": 2
    },
    {
      "level": "H3",
      "text": "from 15.04.2005 onwards. Candidates can submit",
      "page": 2
    },
    {
      "level": "H3",
      "text": "their",
      "page": 2
    },
    {
      "level": "H3",
      "text": "applications",
      "page": 2
    },
    {
      "level": "H3",
      "text": "online",
      "page": 2
    },
    {
      "level": "H3",
      "text": "from",
      "page": 2
    },
    {
      "level": "H3",
      "text": "15.04.2025",
      "page": 2
    },
    {
      "level": "H3",
      "text": "30.04.2025",
      "page": 2
    },
    {
      "level": "H3",
      "text": "https://schooledu.telangana.gov.in",
      "page": 2
    },
    {
      "level": "H3",
      "text": "Examination Centers (Districts) for TG-TET-JUNE-2025:",
      "page": 2
    },
    {
      "level": "H3",
      "text": "TG-TET-JUNE-2025 shall be conducted ONLINE as Computer Based Test between",
      "page": 2
    },
    {
      "level": "H3",
      "text": "15.06.2025 to 30.06.2025. Candidates can submit order of preference of the",
      "page": 2
    },
    {
      "level": "H3",
      "text": "examination centers (district) shown in the online application. However, Convenor, TG-",
      "page": 2
    },
    {
      "level": "H3",
      "text": "TET-JUNE-2025 has the discretion to allot candidates to the examination districts",
      "page": 2
    },
    {
      "level": "H3",
      "text": "depending on the capacity of any particular district.",
      "page": 2
    },
    {
      "level": "H3",
      "text": "Eligibility Criteria:",
      "page": 2
    },
    {
      "level": "H3",
      "text": "The candidates at the time of applying for TG-TET-JUNE-2025 should be in possession",
      "page": 2
    },
    {
      "level": "H3",
      "text": "of the minimum qualifications prescribed for a teacher for I to V classes (Paper-I) and",
      "page": 2
    },
    {
      "level": "H3",
      "text": "VI to VIII classes (Paper-II) as given in Information Bulletin",
      "page": 2
    },
    {
      "level": "H3",
      "text": "The candidates who are pursuing final year of any of the Teacher Education Courses",
      "page": 2
    },
    {
      "level": "H3",
      "text": "recognized by the NCTE or the RCI, as the case may be, and / or the Language Pandit",
      "page": 2
    },
    {
      "level": "H3",
      "text": "Training Courses can also appear for the TG-TET-JUNE-2025.",
      "page": 2
    },
    {
      "level": "H3",
      "text": "09.00 AM to 11.30 AM",
      "page": 2
    },
    {
      "level": "H3",
      "text": "However, it is clarified that appearance or a pass in TGTET by itself will not vest any",
      "page": 3
    },
    {
      "level": "H3",
      "text": "right in a candidate to be considered for appointment to the post of Teacher in",
      "page": 3
    },
    {
      "level": "H3",
      "text": "Government / Zilla Parishad / Mandal Parishad / and Private Aided Schools, which shall",
      "page": 3
    },
    {
      "level": "H3",
      "text": "be in accordance with the relevant statutory recruitment rules framed by State",
      "page": 3
    },
    {
      "level": "H3",
      "text": "Government from time to time.",
      "page": 3
    },
    {
      "level": "H3",
      "text": "Details of qualifications prescribed for TGTET are provided in the Information Bulletin",
      "page": 3
    },
    {
      "level": "H1",
      "text": "10.",
      "page": 3
    },
    {
      "level": "H3",
      "text": "Structure, Content, Syllabus, Initial and Final Key of TG-TET-JUNE-2025:",
      "page": 3
    },
    {
      "level": "H3",
      "text": "The structure and content of each part of Paper-I and Paper-II of the TG-",
      "page": 3
    },
    {
      "level": "H3",
      "text": "TET-JUNE-2025 and the breakup of the total 150 marks among various parts",
      "page": 3
    },
    {
      "level": "H3",
      "text": "of the paper are  given in the Information Bulletin.",
      "page": 3
    },
    {
      "level": "H3",
      "text": "Syllabus",
      "page": 3
    },
    {
      "level": "H3",
      "text": "for",
      "page": 3
    },
    {
      "level": "H3",
      "text": "TG-TET-JUNE-2025",
      "page": 3
    },
    {
      "level": "H3",
      "text": "can",
      "page": 3
    },
    {
      "level": "H3",
      "text": "downloaded",
      "page": 3
    },
    {
      "level": "H3",
      "text": "from",
      "page": 3
    },
    {
      "level": "H3",
      "text": "https://schooledu.telangana.gov.in",
      "page": 3
    },
    {
      "level": "H3",
      "text": "The Director of  School  Education and Chairperson, TGTET is  the",
      "page": 3
    },
    {
      "level": "H3",
      "text": "competent authority to publish the initial key of the question papers after the",
      "page": 3
    },
    {
      "level": "H3",
      "text": "conduct of CBT  inviting  objections  through  online,  if  any,  from  the",
      "page": 3
    },
    {
      "level": "H3",
      "text": "candidates who appeared for the CBT, duly giving a reasonable time to the",
      "page": 3
    },
    {
      "level": "H3",
      "text": "candidates for filing objections on the initial key and the same shall be",
      "page": 3
    },
    {
      "level": "H3",
      "text": "disposed of by the expert committee constituted by the Director of School",
      "page": 3
    },
    {
      "level": "H3",
      "text": "Education and Chairperson, TGTET. The final  key  shall  be  published for",
      "page": 3
    },
    {
      "level": "H3",
      "text": "the information of candidates. Any representation / petition / objection on the",
      "page": 3
    },
    {
      "level": "H3",
      "text": "key after the above stipulated period shall not be entertained.",
      "page": 3
    },
    {
      "level": "H1",
      "text": "11.",
      "page": 3
    },
    {
      "level": "H3",
      "text": "Pass Criteria in TGTET:",
      "page": 3
    },
    {
      "level": "H3",
      "text": "The criteria for considering pass in TGTET is as follows:",
      "page": 3
    },
    {
      "level": "H3",
      "text": "Community",
      "page": 3
    },
    {
      "level": "H3",
      "text": "Pass Marks",
      "page": 3
    },
    {
      "level": "H3",
      "text": "General",
      "page": 3
    },
    {
      "level": "H3",
      "text": "60% and above",
      "page": 3
    },
    {
      "level": "H3",
      "text": "ii) BC",
      "page": 3
    },
    {
      "level": "H3",
      "text": "50% and above",
      "page": 3
    },
    {
      "level": "H3",
      "text": "iii) SC/ ST/ Differently abled (PH)\"",
      "page": 3
    },
    {
      "level": "H3",
      "text": "40% and above",
      "page": 3
    },
    {
      "level": "H3",
      "text": "Note: Physically disabled with at least 40% disability only will be considered in",
      "page": 3
    },
    {
      "level": "H3",
      "text": "respect of visually and orthopedically disabled. With regard to Hearing Impaired,",
      "page": 3
    },
    {
      "level": "H3",
      "text": "minimum 75% disability will be considered under PH category.",
      "page": 3
    },
    {
      "level": "H1",
      "text": "12.",
      "page": 3
    },
    {
      "level": "H3",
      "text": "Validity period of TGTET Certificate / Marks Memo:",
      "page": 3
    },
    {
      "level": "H3",
      "text": "The validity period of TG-TET qualifying certificates for appointment, unless",
      "page": 3
    },
    {
      "level": "H3",
      "text": "otherwise notified by the Government of Telangana, would remain valid for life.",
      "page": 3
    },
    {
      "level": "H1",
      "text": "13.",
      "page": 3
    },
    {
      "level": "H3",
      "text": "Weightage for TGTET Scores in selection in Teacher Recruitment Test:",
      "page": 3
    },
    {
      "level": "H3",
      "text": "TET score shall have 20% weightage in Teacher Recruitment Test in the State of",
      "page": 3
    },
    {
      "level": "H3",
      "text": "Telangana",
      "page": 3
    },
    {
      "level": "H2",
      "text": "14.",
      "page": 4
    },
    {
      "level": "H2",
      "text": "Important dates of TG-TET-JUNE-2025:",
      "page": 4
    },
    {
      "level": "H2",
      "text": "S.No",
      "page": 4
    },
    {
      "level": "H2",
      "text": "Activity",
      "page": 4
    },
    {
      "level": "H2",
      "text": "Time Line",
      "page": 4
    },
    {
      "level": "H2",
      "text": "Date of Notification",
      "page": 4
    },
    {
      "level": "H2",
      "text": "11.04.2025",
      "page": 4
    },
    {
      "level": "H2",
      "text": "Download of TG-TET-JUNE-2025",
      "page": 4
    },
    {
      "level": "H2",
      "text": "Information Bulletin, Detailed Notification",
      "page": 4
    },
    {
      "level": "H2",
      "text": "15.04.2025 onwards",
      "page": 4
    },
    {
      "level": "H2",
      "text": "Payment of Fees Online",
      "page": 4
    },
    {
      "level": "H2",
      "text": "15.04.2025 to 30.04.2025",
      "page": 4
    },
    {
      "level": "H2",
      "text": "Online submission of application through",
      "page": 4
    },
    {
      "level": "H2",
      "text": "https://schooledu.telangana.gov.in",
      "page": 4
    },
    {
      "level": "H2",
      "text": "15.04.2025 to 30.04.2025",
      "page": 4
    },
    {
      "level": "H2",
      "text": "Help Desk services on all working days",
      "page": 4
    },
    {
      "level": "H2",
      "text": "15.04.2025 to 22.07.2025",
      "page": 4
    },
    {
      "level": "H2",
      "text": "Download of Hall Tickets",
      "page": 4
    },
    {
      "level": "H2",
      "text": "09.06.2025 onwards",
      "page": 4
    },
    {
      "level": "H2",
      "text": "Dates of Examination",
      "page": 4
    },
    {
      "level": "H2",
      "text": "Between 15.06.2025 and",
      "page": 4
    },
    {
      "level": "H2",
      "text": "30.06.2025",
      "page": 4
    },
    {
      "level": "H2",
      "text": "Timings of Examination",
      "page": 4
    },
    {
      "level": "H2",
      "text": "9.00 AM to 11.30 AM",
      "page": 4
    },
    {
      "level": "H2",
      "text": "2.00 PM to 4.30 PM",
      "page": 4
    },
    {
      "level": "H2",
      "text": "Declaration of Results",
      "page": 4
    },
    {
      "level": "H2",
      "text": "22.07.2025",
      "page": 4
    },
    {
      "level": "H2",
      "text": "Dated: 11.04.2025",
      "page": 4
    },
    {
      "level": "H2",
      "text": "Director, School Education &",
      "page": 4
    },
    {
      "level": "H2",
      "text": "Chairperson, TGTET",
      "page": 4
    }
  ]
}